fair_mango/__init__.py
fair_mango/typing.py
fair_mango/dataset/__init__.py
fair_mango/dataset/dataset.py
fair_mango/metrics/__init__.py
fair_mango/metrics/base.py
fair_mango/metrics/constants.py
fair_mango/metrics/metrics.py
fair_mango/metrics/superset.py
fair_mango-0.2.1.dist-info/licenses/LICENSE
fair_mango-0.2.1.dist-info/METADATA
fair_mango-0.2.1.dist-info/WHEEL
fair_mango-0.2.1.dist-info/top_level.txt
fair_mango-0.2.1.dist-info/RECORD
